locksmith/__init__.py
locksmith/locksmith.py
locksmith/main.py
locksmithy/__init__.py
locksmithy/locksmith.py
locksmithy-0.1.0.dist-info/METADATA
locksmithy-0.1.0.dist-info/WHEEL
locksmithy-0.1.0.dist-info/entry_points.txt
locksmithy-0.1.0.dist-info/top_level.txt
locksmithy-0.1.0.dist-info/RECORD
