Metadata-Version: 2.1
Name: locksmithy
Version: 0.1.0
Summary: A simple password generator
Home-page: https://github.com/llyram/locksmithy
Author: Maryll Castelino
Author-email: maryllcastelino@gmail.com
Classifier: Programming Language :: Python :: 3
Classifier: License :: OSI Approved :: MIT License
Classifier: Operating System :: OS Independent
Requires-Python: >=3.6
